opensts_py/.env
opensts_py/.env_example
opensts_py/.git/COMMIT_EDITMSG
opensts_py/.git/HEAD
opensts_py/.git/config
opensts_py/.git/description
opensts_py/.git/hooks/applypatch-msg.sample
opensts_py/.git/hooks/commit-msg.sample
opensts_py/.git/hooks/fsmonitor-watchman.sample
opensts_py/.git/hooks/post-update.sample
opensts_py/.git/hooks/pre-applypatch.sample
opensts_py/.git/hooks/pre-commit.sample
opensts_py/.git/hooks/pre-merge-commit.sample
opensts_py/.git/hooks/pre-push.sample
opensts_py/.git/hooks/pre-rebase.sample
opensts_py/.git/hooks/pre-receive.sample
opensts_py/.git/hooks/prepare-commit-msg.sample
opensts_py/.git/hooks/push-to-checkout.sample
opensts_py/.git/hooks/sendemail-validate.sample
opensts_py/.git/hooks/update.sample
opensts_py/.git/index
opensts_py/.git/info/exclude
opensts_py/.git/logs/HEAD
opensts_py/.git/logs/refs/heads/main
opensts_py/.git/logs/refs/remotes/origin/HEAD
opensts_py/.git/logs/refs/remotes/origin/main
opensts_py/.git/objects/0b/14be2e6261b7e2c6de3c75348974aba688c146
opensts_py/.git/objects/1a/801192a414074358a7fb0ee23a112895305985
opensts_py/.git/objects/20/5cb5e168fab244b793a8a52c52fdcc51e89bb0
opensts_py/.git/objects/2b/49af6cb56b3bb97ab5191b52968af1e565148d
opensts_py/.git/objects/3c/e61069ebcbff7fcd2a24ada91b3b172887b948
opensts_py/.git/objects/3f/a23c55d9156bd28744d9e47407398137b9dfb0
opensts_py/.git/objects/51/d6a8814bfcf34ca0105cf118135efdae365199
opensts_py/.git/objects/76/b8f80bcd6aa0a9d53fc5d464dd888710e25417
opensts_py/.git/objects/77/adf6c0c5b21fec2481f4e3c7548910b7d8c61c
opensts_py/.git/objects/96/4ba50a660d3ded19d3959616ea9822ad8976af
opensts_py/.git/objects/b6/e87b8f01638a31a6d1237bdac21ba05cee5c9e
opensts_py/.git/objects/ca/81ee6f284771e52ec026ccc229ecdd16f25b17
opensts_py/.git/objects/cc/34790454e98c91390fa52c77baa81b1454e98a
opensts_py/.git/objects/ce/c150869f0e6e5a5141032ea24f2a514abc37b2
opensts_py/.git/objects/dc/ef21a37a329aab02a7a410517ed96476477617
opensts_py-0.1.2.dist-info/METADATA
opensts_py-0.1.2.dist-info/WHEEL
opensts_py-0.1.2.dist-info/RECORD
