Metadata-Version: 2.1
Name: opensts-py
Version: 0.1.2
Summary: This is a demo for accessing data using MQTT and OpenSTS services
Author: PratikANaik
Author-email: pratik.naik@alltrons.com
Requires-Python: >=3.12,<4.0
Classifier: Programming Language :: Python :: 3
Classifier: Programming Language :: Python :: 3.12
Classifier: Programming Language :: Python :: 3.13
Requires-Dist: paho-mqtt (>=2.1.0,<3.0.0)
Requires-Dist: python-dotenv (>=1.0.1,<2.0.0)
